{"title": "Fergie's", "meter": "6/8", "version": 1, "link": "https://thesession.org/tunes/11709#setting11709", "tune": "B | Bee efg | fed Bee | d2B ABA | FGA B2A |\nBee efg | fed BAG | FGA BAG | FEE E2 :|\nz | B2A BEE | EFG F2E | F2A d2e | fed BAF |\nB2A BEE | EFG F2E | FGA BAG | FEE E2 :|\nB | Bee gee | Bee BAG | FAA dAA | FGA B2A |\nBee gee | Bee BAG | FGA BAG | FEE E2 :|\nz | BEE BEE | EFG F2E | DFA d2e | fed BAF |\nBEE BEE | EFG FEF | DFA BAG | FEE E2 :|\r\r\n", "key": "Emin", "type": "jig", "unit": "1/8"}