{"title": "Lost Purse, The", "meter": "4/4", "version": 1, "link": "https://thesession.org/tunes/4912#setting4912", "tune": "D2|:B>ABG cBce|dGBd g2a>g|eag>e d^c=cB|A>BAG F2D2|\nB>ABG cBce|dGBd ef/e/ dc|B>cdB c/B/A FA|1 B2GF G2dc:|2 B2GF G2Bd||\ng>fgb agfe|d>edc Bc/B/ AB|c>Bce dBcB|A>BAG F2D2|\ng>fgb agfe|dGBd ef/e/ dc|B>cdB c/B/A FA|B2GF GABd|\ng>fgb agfe|d>edc Bc/B/ AB|c>Bce dBcB|A>BAG F2GA|\nB>ABG cBce|dGBd ef/e/ dc|B>cdB c/B/A FA|B2GF G2||\r\r\n", "key": "Gmaj", "type": "barndance", "unit": "1/8"}