{"title": "Boys Of The Lough, The", "meter": "4/4", "version": 6, "link": "https://thesession.org/tunes/343#setting23073", "tune": "|:A~D3 F~A2B | defd ecdB |\"A\" (3.A.c.A FA dBAF |(3GFE FD E2 FG |\nA~D3 F~A2B | defd ecdB | (3.A.c.A FA dBAF |1 GFEG FDD2 :|2 GFEG FDD :|\nf|:af (3.g.f.e fdec | dcBA BcdB | (3.A.c.A FA dAFA|\"B\" EGFD E2fg |\naf (3.g.f.e fdec | dcBA BcdB | (3.A.c.A FA dAFA | GFEG FDD2 :|\n\"Variations\" \"A\"A~F3 d~F3 | E^DEF E2FG |\"B\" (3GFE FDE2 fg |\r\r\n", "key": "Dmaj", "type": "reel", "unit": "1/8"}