{"title": "Smelling Fresh", "meter": "4/4", "version": 3, "link": "https://thesession.org/tunes/13197#setting25295", "tune": "[M:7/8]|:cd d2 AdA|Bd eB dBA|Be e2 edA|Be ef aaa|\n| cd d2 AdA|Bd eB dBA|Be ef aaa|af ef edB:|\n|: cd d2 AdA|Bd eA dBA d2 A|Be e2 edA|Be ef afe|\n|cd d2 AdA |cd ed dBA|Be ef aaa|af ef edd:|\n|:fa a/a/a fae|ff fa eff|Aa Aa fea|fe dA BBB|\n|AB BA d2 A|ef Aa fed|Bd ef aaa|af ef edB:|\n|: fa a/a/a fae|ff fa eff|Aa Aa aAa|fe ad ABB|\n|AB BA d2 A|ef Aa fed|Bd ef aaa|af ef edB:|\r\r\n", "key": "Dmaj", "type": "reel", "unit": "1/8"}