{"title": "Fanny Power", "meter": "6/8", "version": 4, "link": "https://thesession.org/tunes/957#setting23148", "tune": "V:1\nD|\"G\"G2D GAB | \"C\"c2B A2G |\"D\"F2E DFD |\"D\"F2G A2c |\nV:2\nd|g2g g2d | c2c c2e | d2d dcB | ded cBA |\nV:1\n\"G\"BAG Bcd | \"C\"e2A A2G | \"C\"F2E DGF | \"G\"G3 G3 :||\nV:2\nG2G GAB | c2c c2e | d2d def | gdB G3 :||\nV:1\nBc|\"G\"dB/c/d \"D\"dB/c/d | \"Em\"GBG \"G\"GBG | \"C\"ec/d/e ec/d/e | \"D\"AcA AcA |\nV:2\nzz|g3 f3 | g3 d3 | c3 B3 | c3 A3 |\nV:1\n\"G\"Bcd \"C\"efg | \"D\"fga dec | \"G\"BAG \"D\"(3A/B/c/AF | \"G\"G3 G3 :||\nV:2\nBAG FGE | DcB c2E | GAB cAF | G3 GBd :||\r\r\n", "key": "Gmaj", "type": "jig", "unit": "1/8"}