{"title": "Tales Of Peedy And Paddy, The", "meter": "6/8", "version": 1, "link": "https://thesession.org/tunes/8440#setting8440", "tune": "|:\"Em\"BAB G2G|\"Em\"A2A d2\"Bm\"G|\"Em\"BAB G2G|\"G\"FED D2E|\n\"Em\"BAB G2G|\"Em\"A2A d2\"Bm\"c|\"Em\"Bcd cdf|\"G\"G3 ez2:|\ngdG g2d|gdG g2d|edc B2c|fed def|\ngdG g2d|gdG g2d|fga bag|fed dcg|\ngdG g2d|gdG g2d|edc B2c|fed def|\ngdG g2d|gdG g2d|fga bag|fed dcg||\ngdG g2d|gdG g2d|edc B2c|fed def|\ngdG g2d|gdG g2d|fga bag|fed dcg|\ng2d gdG|g2d gdG|GEG Bed|fed def|\ng2d gdG|g2d gdG|dBg aBg|deB Bcd|g6||\r\r\n", "key": "Emin", "type": "jig", "unit": "1/8"}