{"title": "Mulqueeney's", "meter": "4/4", "version": 1, "link": "https://thesession.org/tunes/2771#setting2771", "tune": "|:(3GBd g2 fedf | eAce d2 gf | e2 ce dGBd | cBAG F2 D2 |\n(3GBd g2 fedf | eAce d2 gf | e2 ce dGBd | cAFA G4 :|\n|:(3GBd g2 (3GBd g2 | (3GBd gB eB d2 | (3FAd f2 (3FAd f2 |(3FAd fe (3ded (3cBA|\n(3GBd g2 (3GBd g2 | (3GBd gB eBdg | f2 ed eA^ce |1 dgfe (3ded (3cBA :|2 dgfe defg ||\n|: a2 ba afab | afab a2 fe | defg adfa | bfge defg |\na2 ba afab | afab a2 fe | de (3fed (3Bcd AF |1 G2 Bd defg :|2 G2Bd (3gfe (3dBA ||\r\r\n", "key": "Gmaj", "type": "hornpipe", "unit": "1/8"}