{"title": "Mrs. Jane Kennedy Of St. Anne's, Methven", "meter": "3/4", "version": 1, "link": "https://thesession.org/tunes/15556#setting29161", "tune": "d>c|:B2A>G A<d|A4d>c|B<A AG f<g|(e2 e)e f>d |\nB<A AG d<c|(A2 A)G A/B/d | e2 A>G g<a |[1 d3A d>c :|[2 d4 f>g|\n|:a2d>G g<f| B4e>f| g2f>d d<c|A4 e/f/g|a2d>G f<g|\n(B2B)A A/B/d|e2A>G g<a|[1d4f>g:|[2d3A d<c|\n|:(B2B)A A/B/d|e2A>A A/B/d | f2e>d f<a|(B2B)A A/B/d|\ne2A>A A/B/d|f<ad2 c<d|(G2G)>g g<a|[1d3A d<c:|[2d4cd|\n|:(e2e)A de|fe d>d c<d|B2A>G f<g|(e2e)e fg|\n(a2a)d c<d|(G2G)A A/B/d|e2 A>G g<a|[1d4 cd:|[2d3|\r\r\n", "key": "Dmaj", "type": "mazurka", "unit": "1/8"}