{"title": "Blackbird, The", "meter": "4/4", "version": 6, "link": "https://thesession.org/tunes/1104#setting26494", "tune": "dc|:BGBd cA{A}BG|(3ABA GB ABcA|d2de dcAF|GB{B}AF D2DE|{G}FEFG Adfe|\nd2de dcAF|1 [M:3/2] GB{B}AF D2 D2 D2dc:|2 [M:3/2] GB{B}AF D2 D2 D2de||\n|: [M:C|] {g}fede {fg}f2g2|a2ag fg{b}af|g2{ga}gf gbaf|ga{a}gf d2de|\n{g}fede {fg}f2g2|a2ag fg{b}af| [M:3/2] ga{a}gf d2dc defg|\n[M:C|] a2ag fg{b}af|ga{ga}ge (3fgf ef|dcAG ABcd|ef{a}ge {ab}a2a2|AB{B}AG FGAB|\nc2ce dcAF|1 [M:3/2] GB{B}AF D2D2 D2de:|2 [M:3/2] GB{B}AF D2D2 D2||\r\r\n", "key": "Dmix", "type": "hornpipe", "unit": "1/8"}