{"title": "Cavan Potholes", "meter": "4/4", "version": 1, "link": "https://thesession.org/tunes/3393#setting3393", "tune": "e- edBA | G2Bd BAGB | AD~D2 ADFD | EFGE AGFA | GABd edBA |\nG2Bd BAGB | A2de dABd | e2~e2 defd | e2BA (3Bcd ef |\ngfef gfeg | fedB ABdf | eBBA BedB | ABdB ADFD |\nE2Bd BAGB | AGFE DEFD | EFGE FEDF | ~E3 :|\n|:A (3Bcd ef | g3a gfeg | fedB ABdf | eBBA BdeB | BAGA (3Bcd ef |\n~g3a gfeg | (3fed ag fefd | ebaf g2Bg | fde2 (3Bcd ef |\ngaba gfeg | fgfe de (3fed | egfa gedg | (3efg fd BdAF |\nG2Bd BAGB | AGFE DEFD | EFGE AGFG | ~E3 :|\r\r\n", "key": "Dmaj", "type": "reel", "unit": "1/8"}