{"title": "Hag At The Spinning Wheel, The", "meter": "6/8", "version": 6, "link": "https://thesession.org/tunes/2254#setting25872", "tune": "D|:G3 B2G|BcA B2D|Gc/A/G cAG|F3 AFD|\nGc/A/G B2G|BcA B2c|df/g/d cAF|1AGF G2D:|2AGF G2c||\n|:BAG AFD|D3 AFD|D3 AFD|EFG ABc|\nBAG AFD| D3 AFD|df/g/d cAF|1AGF G2c:|2AGF G2D||\n|:GB/c/d gba|gdB ecA|dBG cAG|F2G AFD|\nGB/c/d gba|gdB ecA|fed cAF|1AGF G2D:|2AGF G2A||\n|:c/B/AG Afd|Bfd Afd|Bfd AFD|EFG ABc|\nBAG AFD|D3 AFD|df/g/d cAF|1AGF G2A:|2AGF G2D||\r\r\n", "key": "Gmaj", "type": "jig", "unit": "1/8"}