{"title": "Down And Out In Santiago De Compestella", "meter": "3/4", "version": 1, "link": "https://thesession.org/tunes/7362#setting7362", "tune": "|: fg | af f/f/f df | df fd ef | ge e/e/e ce | ce eA AF |\nGA BG GB | AB cA AA |[1 cd eA fa | e4 :|[2 ca ge cd | ed dd ||\n|: ag | fd d/d/d df | df f/f/f gf | ec c/c/c ce | ce e/f/e AB |\n[1 dB B/B/B Bd | Bd d/d/d dB | AB cd ef | g4 :|\n[2 GA BG GB | AB cA A/A/A | cage cd ed | d4 ||\n|: A2 | d2 fd ec | d4 A2 | d2 ed cB | A4 AB |\nGA BG GB | AB cA A/A/A |1 cd eA fa | e4 :|2 ca ge ed | d4 ||\r\r\n", "key": "Dmaj", "type": "mazurka", "unit": "1/8"}