{"title": "Space Available", "meter": "4/4", "version": 1, "link": "https://thesession.org/tunes/4258#setting4258", "tune": "D |: G2 B>A B2-B>c | B>A G<B d2-d>B | c2 c<e d2-d>B |c>B A>G F<A D>F |\nG2 B>A B2-B>c | B>A G<B d2-d>B | c2 c<e d2-d>B | c>B A>F G2-G>F :|\nG2 g>f g2 d>g | b>a g>f g2-g>B | c2 e2 d2-d>B | c>B A>G F<A D>F |\nG2 g>f g2 d>g | b>a g>f g2-g>B | c2 c<e d2-d>B | c>B A>G F<A D>F |\nG2 g>f g2 d>g | b>a g>f g2-g>B | c2 e2 d2-d>B | c>B A>G F<A D>F |\nG2 B>A B2-B>c | B>A G<B d2-d>B | c2 c<e d2-d>B | c>B A>F G4 ||\r\r\n", "key": "Gmaj", "type": "strathspey", "unit": "1/8"}