{"title": "Champion, The", "meter": "4/4", "version": 3, "link": "https://thesession.org/tunes/2031#setting24870", "tune": "(ude)|f>=ef>g f>_ed>c|{c}B>AB>c d>BF>D|\\\nE>Gc>e D>FB>d|((3cdc) ((3BAG) F2(de)|\nf>=ef>g f>_ed>c|{c}B>AB>c d>BF>D|\\\nE>Gc>e d>cB>A|B2d2B2:|\n|:(uAB)|c>f=e>f a>fe>f|d>g^f>g b>gf>g|(db)(ca) (Bg)(Af)|\nG>bg>=e f2(AB)|c>f=e>f a>fe>f|d>g^f>g b>gf>g|\n|1 (db)(ca) (Bg)(Af)|G>bg>=e f2:|2 (db)(ca) (Bg)(d=e)|f>_ec>A F2(de)|]\r\r\n", "key": "Gmin", "type": "hornpipe", "unit": "1/8"}