{"title": "Sherlock's", "meter": "4/4", "version": 2, "link": "https://thesession.org/tunes/713#setting13782", "tune": "|: (3GAB |c>d (3cBA G>FE>G | c>Gc>d e>gc\u2019>b | a>gf>e d>ec>d | e>dc>B (3ABA (3GAB |\nc>d (3cBA G>FE>G | c>Gc>d e>gc\u2019>b | a>gf>e d>ec>d | e>cc>B c2 :|\n|: (3efa |g>eg>a g>ec>G | c>eg>a (3gc\u2019g c\u2019>b | ~a2c\u2019>a g>ec>e | (3faf (3ege d>cA>B |\nc>d (3cBA G>FE>G | c>Gc>d e>gc\u2019>b | a>gf>e d>ec>d | e>cc>B c2 :|\r\r\n", "key": "Cmaj", "type": "hornpipe", "unit": "1/8"}