{"title": "Patrick's Park", "meter": "4/4", "version": 1, "link": "https://thesession.org/tunes/11609#setting11609", "tune": "E |\"D\"D3E \"Bm\"FABc |\"D\"dfed \"A\"cBAc |\"G\"d2BG \"D\"FGAB |\"A\"ABcA GECE |\n\"D\"D3E \"Bm\"FABc | \"D\"dfec defg |\"F#m\"afec \"Bm\"BcdB |\"A7\"AGFE \"D\"D3 :|\nc |\"D\"dcdf \"Em\"edBc |\"D\"defg \"A7\"agec |\"D\"d2fd adfd |\"Em\"B2eB \"A7\" gfec |\n\"D\"dcdf \"Em\"edBc | \"D\"defg \"Bm7\"afbf | \"G\"gfeg \"Bm\"fedB | \"A\"ABce \"D\"d3 :|\r\r\n", "key": "Dmaj", "type": "reel", "unit": "1/8"}