{"title": "Winter Night Schottische, The", "meter": "4/4", "version": 2, "link": "https://thesession.org/tunes/4765#setting21764", "tune": "K: CMaj\nc'2 e>f g2 c>d | e>Bc>A G4 | G>AB>c d>ef>g | a2 g>^f g4 |\nc'2 e>f g2 c>d | e>Bc>A G4 | G>AB>c d>ef>B | c2 c>B c2 z2 ||\n|: A2 A>^G A>Bc>d | e2 e>^d e2 a2 | e2 a2 e2 d2 | c>dc>B A2 E2 |\nA2 A>^G A>Bc>d | e2 e>^d e2 a2 | e2 d>e c>dB>c |[1 A2 z2 a2 z2 :|[2 A2 z2 [B2g2] z2 ||\nc'2 e>f g2 c>d | e>Bc>A G4 | G>AB>c d>ef>g | a2 g>^f g4 |\nc'2 e>f g2 c>d | e>Bc>A G4 | G>AB>c d>ef>B | c2 c>B c2 z2 ||\nK: FMaj\n|: \"trio\"f2 fa cfAc | FAcf a4 | g2 gb egce | Gceg b4 |\nf2 fa cfAc | FAcf a3 f | efga bcde | f2 f2 f2 z2 :|\nK: CMaj\nc'2 e>f g2 c>d | e>Bc>A G4 | G>AB>c d>ef>g | a2 g>^f g4 |\nc'2 e>f g2 c>d | e>Bc>A G4 | G>AB>c d>ef>B | c2 c>B c2 \"fine\"z2 |]\r\r\n", "key": "Gmaj", "type": "barndance", "unit": "1/8"}