{"title": "Hoppy, The", "meter": "4/4", "version": 1, "link": "https://thesession.org/tunes/4592#setting4592", "tune": "|: G2 ^cd cd cd | de cA F2 z2 | de cA F2 z2 | de BG D2z2 |\nG2 ^cd cd cd | de cA F2 z2 | de cA F2 B2 |1 G4 B2 A2 :|2 G4 g2 f2 ||\n|: e3^d ef ge | d2 dc Bc dB | A2 d^c de fg | a4 f2 d2 |\nB3/2c/ BA cd gf | fe ^df e2 fe | (3d^de fe =d^c =cA |1 (3GAG FA G2 gf :|2 (3GAG FA G4 ||\n\"VARIATIONS ON BARs 1 to 6\"\nG2 ^cd cd cd | de cA FF z2 | de cA FF z2 | de BG DD z2 | \\ G2 ^cd cd cd | de cA FF z2 |\r\r\n", "key": "Gmaj", "type": "hornpipe", "unit": "1/8"}