{"title": "Cahir's Kitchen", "meter": "4/4", "version": 4, "link": "https://thesession.org/tunes/1090#setting25907", "tune": "|:B|E2GB E2GB|A2FA DEFD|E2GB E2GA|B3A BAGF|\nE2GB E2GB|A2FA dAFD|(3EFG FA GBAc|BAFG E4||\n|:A|BEGB EG B2|A2 FA DEFD|BeBG EFGE|BGcA dBcA|\nB3G EG B2|A2FA dAFD|(3EFG FA GBAc|BAFG E3f||\n|:eBgf eBfe|dAfe dAgf|eBgf eB B2|BAGF GE E2|\neBgf eBfe|dA A2 FAd2|(3EFG FA GBAc|BAFG E3f||\neBgf eBfe|dAfe dAgf|eBgf e3f|g3a bagf|\neBgf eBfe|dA A2 FAd2|(3EFG FA GBAc|BAFG E4||\r\r\n", "key": "Emin", "type": "reel", "unit": "1/8"}