{"title": "March Of King Laois, The", "meter": "2/4", "version": 1, "link": "https://thesession.org/tunes/15858#setting29829", "tune": "{g}e{A}ec {gef}e2 A | {g}e{A}ec {gef}e2 A | {g}f{e}fd {gef}e2 c | {Gdc}d2 c {gBd}B2 {G}A |\n%\n[1 {g}e{A}ec {gef}e2 A | {g}e{A}ec {gef}e2 a |[2 {gef}e2 c {gef}e2 A | {gef}e2 c {gef}e2 a |\n%\n{fg}f2 a e>ad | {g}ca2/4c {gBd}B2 {G}A | {gcd}c2 {e}A {Gdc}d2 B | {gef}e3 {A}e>dc |\n%\n{g}B>gd {g}B>GB | {g}d>gd {g}B>GB | {g}A>BA {g}A>BA | {g}A>BA {g}A>BA :|\n|: {g}f{e}fd {ag}a2 d | {g}f{e}fd {ag}a2 d | {gef}e2 a {ef}e2 c | {gef}e2 a {ef}e2 g |\n%\n{fg}f2 a {g}a2 e | {g}d>gd {g}B>cd | {g}c>eA {g}d>ef | {gef}e3 {A}e>dc |\n%\n{g}B>gd {g}B>GB | {g}d>gd {g}B>GB | {g}A>BA {g}A>BA | {g}A>BA {g}A>BA :|\n|: {gef}e2 c {gef}e2 A | {gef}e2 c {gef}e2 A | {gfg}f2 d {gef}e2 c | {Gdc}d2 c {gBd}B2 {G}A |\n%\n{gef}e2 c {gef}e2 A | {g}e{A}ec {gef}e2 a | {fg}f2 a e>ad | {g}c>ac {gBd}B2 {G}A | {gcd}c2 {e}A {Gdc}d2 B | {gef}e3 {A}e>dc |\n%\n{g}B>gd {g}B>GB | {g}d>gd {g}B>GB | {g}A>BA {g}A>BA | {g}A>BA {g}A>BA :|\n|: {gfg}f2 d {ag}a2 d | {gfg}f2 d {ag}a2 d | {gef}e2 a {ef}e2 c | {gef}e2 a {ef}e2 g |\n%\n{fg}f2 a {g}a2 e | {g}d>gd {g}B>cd | {g}c>eA {g}d>ef | {gef}e3 {A}e>dc |\n%\n{g}B>gd {g}B>GB | {g}d>gd {g}B>GB | {g}A>BA {g}A>BA | {g}A>BA {g}A>BA :|\r\r\n", "key": "Dmaj", "type": "polka", "unit": "1/8"}