{"title": "Hole In The Boat, The", "meter": "6/8", "version": 4, "link": "https://thesession.org/tunes/1585#setting24270", "tune": "E || ~A3 ABA | A(3Bcd egb | {c\u2019}age (fg)e | dBG {a}edB |\n~A3 ABA | A(3Bcd egb | {c\u2019}age g z e | dBG ~A2 E ||\nAEA ~B2A | A(3Bcd ~e3 | {c\u2019}age (fg)e | dBg edB |\n~A3 ABA | A(3Bcd egb | {c\u2019}age g z e | dBG A(3Bcd |]\neaa aba | {c\u2019}age (fg2) | {c\u2019}ag(e g) z e | dBG {a}edB |\n~A3 ABA | A(3Bcd egb | {c\u2019}age g z e | dBG A(3Bcd ||\neaa eaa | {c\u2019}age (gfg) | age g z e | dBG {a}edB |\n~A3 ABA | A(3Bcd egb | {c\u2019}age (fg)e | dBG ~A2E |]\r\r\n", "key": "Ador", "type": "jig", "unit": "1/8"}