{"title": "Madoline O'Connell, The", "meter": "6/8", "version": 1, "link": "https://thesession.org/tunes/16315#setting30890", "tune": "|: \"D\" F2Ad2A  |F2Ad2A| \"G\" (BAB) (ede) | \"A\" (fdB) (ABc) |\"D\" F2Ad2A |  F2Ad2A | \"G\" (BAB) (ede) | \"D\" (fdB) d3  :|\n|:\"D\" f2f (fed) | \"C\" e2e (edc)  | \"Em\" d2d (ede) |\"D\" (fde) A3   |  f2f (fed) |\"C\" e2e (edc)  | \"G\" d2d (ede) | \"D\" (fdc) d3  :|\n|:\"D\" f2a (agf) |\"C\" e2g (gfe)  | \"G\" d2e (fde) |\"A\" (fde) A3   |  \"D\" f2a (agf) |\"C\" e2g (gfe)  | \"G\" d2e (fde) |\"D\"  (fde) d3  :|\r\r\n", "key": "Dmaj", "type": "jig", "unit": "1/8"}