{"title": "Up And About In The Morning", "meter": "6/8", "version": 3, "link": "https://thesession.org/tunes/3145#setting25236", "tune": "|:A2D D3 | ABG A2d | cAG EFG | F/G/AD EFG |\nA3 DAD | ABG A2 d | cAG EFG |1 FAD D3|2FAD D2A :|\n|:d2e g/f/ed | ege dcA | A3 EFG | FAD EFA |\nd2e f.c/.A/f | ege dcA | A.F/.G/A EFG | FAD D3:|\n|:d.f/.g/d dcA | ded dcA | A.F/.G/A AGE | A.F/.G/A ABc |\nd2 e f3 | ege dcA | A3 EFG | FAD D3|\nd.f/.g/d dcA | ded dcA | A.F/.G/A AGE | A.F/.G/A ABc |\nd.f/.g/d f.c/.A/f|e.c/.A/e d.f/.g/d|A.F/.G/A EFG|FAD D3||\r\r\n", "key": "Dmaj", "type": "jig", "unit": "1/8"}