{"title": "Beauty Spot, The", "meter": "4/4", "version": 4, "link": "https://thesession.org/tunes/1270#setting14582", "tune": "F3E F2BA|F2EC A,B,CE|~F3E ~F2BA|FAEA, CB,CE|\r~F3E F2BA|F2EC A,B,CE|~F3A ~G3B|AFEA, CB,CE||\rcBAB cB~B2|ceAB cafe|cBAB cB~B2|EFAB cB~B2|\rc2AB cB~B2|ceAB cafe|~c3A BcBA|EFAB cABA||\rB3A B2ed|B2AF DEFA|~B3A ~B2ed|BdAD FEFA|\r~B3A B2ed|B2AF DEFA|~B3d ~c3e|dBAD FEFA||\rfede fe~e2|fade fbba|fede fe~e2|ABde fe~e2|\rfede fe~e2|fade fbba|~f3d efed|ABde fded||\rA3G A2dc|A2GE CDEG|~A3G ~A2dc|AcGC EDEG|\r~A3G A2dc|A2GE CDEG|~A3c ~B3d|cAGC EDEG||\redcd ed~d2|egcd eaag|edcd ed~d2|GAcd ed~d2|\redcd ed~d2|egcd eaag|~e3c dedc|GAcd ecdc||\rA3G A2dB|BccG DEGE|GA (3BAG AdcA|BAGd edBG|\rA3G A2dB|BccG DEGE|GA (3BAG AdcA|BAGd edd2||\reddA ed~d2|edcd efgd|e2dA edcA|GAcd edd2|\re2dA edcd|edcd efg2|fgef decd|ABcA GA (3BAG||\rVariations for the last bar are |BcAB GAEG| and |ABGA EFGE| \rA3G A2dB|~c3G EFGE|A2AG AddB|cBcG EDDG|\rA3G A2dB|~c3G EFGE|A3c ~B3d|cBcG EDD2||\red~d2 edcd|ed~d2 eaag|ed~d2 edcA|GAcd ed~d2|\red~d2 edcd|ed~d2 eaag|fgef decA|GAcd egdc||\r\r\n", "key": "Dmix", "type": "reel", "unit": "1/8"}