{"title": "Mason's Men", "meter": "4/4", "version": 1, "link": "https://thesession.org/tunes/4154#setting4154", "tune": "\"Basic melody\"\n|d2 cd ecde|a2 ga fdec|dBcd ecde|f2 ec d2 fe|\n|d2 cd ecde|a2 ga fdec|dBcd ecde|faec d2 de||\n|f B3 FB3|ceag fede|f B3 FB3|ABcd Bcde|\n|fB3 FB3|ceag fede|fB3 FB3|ABcd BABc||\n\"As played\"\n|d2 cd ecde|(3aba ga fdec|dBcd ecde|(3fgf ec dgfe|\n|d/d/d cd ecde|(3aba ga fdec|dAB/c/d ecde|faec dcde||\n|f ~B3 F~B3|ceag fede|f~ B3 F~B3|ABcd Bcde|\n|fBFB DFBd|ceag fede|~f3d BFBd|ABcd efge||\r\r\n", "key": "Dmaj", "type": "reel", "unit": "1/8"}