{"title": "Seven Hops", "meter": "3/4", "version": 4, "link": "https://thesession.org/tunes/3628#setting16624", "tune": "B2 D2 G2 | B2 G2 D2 | C2 E3 G | c4 E2 | \rD2 F2 A2 | c2 A2 c2 | B2 G2 E2 | D4 C2 |\rB2 D3 G | B2 G2 D2 | C2 E2 G2 | c4 E2 | \rD2 F2 A2 | c2 d3 c | B2 G2 F2 | G4 :|\rB4 Bd | c2 B3 A | G2 C2 E2 | D3 D GB | \rc2 cB A>F | D2 F2 A^A | B3 G E2 | D4 G2 |\rB2 B3 d | (3cdc B2 A2 | G2 C2 E2 | D4 d2 | \rc2 d/c/B A>F | D2 F3 c | B2 G2 G2 | G4 :|\r\r\n", "key": "Gmaj", "type": "waltz", "unit": "1/8"}