{"title": "Al-Al\u00e1ndalus, The", "meter": "4/4", "version": 1, "link": "https://thesession.org/tunes/14170#setting25719", "tune": "bfff gfed | efff gfeg | fb c'd'2c' c'b | b^aag gfef | bfff gfed |\nefff gfeg | f^e =ec2^A cg | edc^A B2fa | bfff gfed |\nefff gfeg | fb c'd'2c' c'b | b^aag gfef | bfff gfed |\nefff gfeg | f^e =ec2^A cg | edc^A B2 F^A | BFFF BFcF |\nFFcF dFFF | B^A cf2efg | f^eed dcc^A | BFFF BFcF |\nFFcF dFFF | B^A cf2efg | edc^A B2 F^A | BFFF BFcF |\nFFcF dFFF | B^A cf2efg | f^eed dcc^A | BFFF BFcF |\nFFcF dFFF | B^A cf2efg | edc^A B4 |\r\r\n", "key": "Bmin", "type": "reel", "unit": "1/8"}