{"title": "Swan, The", "meter": "4/4", "version": 4, "link": "https://thesession.org/tunes/1036#setting14267", "tune": "|: G2 (3BAG d>GB>d | g2 f>g e>gd>B | c>Ae>c (3Bcd G>B | A>DF>A d>Bc>A |\rG2 (3BAG d>GB>d | g2 f>g e>gd>B | c>Ae>c (3Bcd G>B | A>DF>A G3z :|\r|: g>GB>g f>Ac>e | e>d (3BAG A>D (3FED | G>B (3BBB c>ea>g | (3fga e>a ^c>de>f |\rg>GB>g f>Ac>e| e>d (3BAG A>D (3FED | G>B (3BBB c>ea>g | (3fed (3cBA G>AB>d :|\r|: ~g2- g>b g>dB>d | c>BA>G F>Ad>c | B>Gg>f e>^ca>g | (3fga e>a ^c>de>f |\rg>GB>g f>Ac>e | e>d (3BAG A>D (3FED | G>B (3BBB c>ea>g |[1 (3fed (3cBA G>AB>d :|[2 f/e/dc/B/A G3z |]\r\r\n", "key": "Gmaj", "type": "hornpipe", "unit": "1/8"}