{"title": "Czar Of Munster, The", "meter": "4/4", "version": 1, "link": "https://thesession.org/tunes/7588#setting7588", "tune": "\"Intro:\"c'AAb AAaA|d'AAc' AAbA|e'AAd' AAc'A|f'Ae'A d'Ac'A|\nc'AAb AAaA|d'AAc' AAbA|e'AAd' AAc'A|f'Ae'A d'Ac'A|\nc'AAb AAaA|d'AAc' AAbA|e'AAd' AAc'A|f'Ae'A d'Ac'A|\nc'AAb AAaA|bAAa AAgA|aAAg AAfA|Aeed eABc|\n\"Main Tune:\"|:A2 (3AAA aAgA|(3AAA fA eABc|cBBA ^GABc|ABcd ecBc|\nA2 (3AAA aAAb|AAc'A c'AaA|^gaba ageg|baa^g aAde|\nfdAD FAcd|ecAF EABc|cBBA ^GABc|ABcd eAde|\nfdAD FAcd|ecAF EABc|cBBA ^GABc|1 (3ccc Bc ABcB:|2 (3ccc Bc A^GAB||\nc2 (3dcB cdef|g2 (3ag^f ge=fe|defg defg|eccB cGAB|\nc2 (3dcB cdef|g2 (3ggg ^g2 (3ggg|a2 fe defg|eccB cAde|\nfdAD FAcd|ecAF EABc|cBBA ^GABc|ABcd eAde|\nfdAD FAcd|ecAF EABc|cBBA ^GABc|1 (3ccc Bc A^GAB:|2 (3ccc Bc ABcB||\r\r\n", "key": "Amin", "type": "reel", "unit": "1/8"}