{"title": "Far Away", "meter": "3/4", "version": 1, "link": "https://thesession.org/tunes/187#setting187", "tune": "z4 FA |B2 BA Bd |cA F2 FA |B2 BA B3/4c/e3/4 |\nc4 dc |B2 BA B3/4c/d3/4 |cB A2 de |fe dc BA |\nB3 A FA |B2 BA Bd |cA F2 FA |B2 BA B3/4c/e3/4 |\nc4 dc |B2 BA B3/4c/d3/4 |cB A2 de |fe dc BA |\nB3 c de |f2 fe f3/4g/a3/4 |ec A2 de |f2 fe f3/4g/a3/4 |\ne4 de |fd Be cA |dB Gd BG |F2 B2 BA |\nB3 c de |f2 fe f3/4g/a3/4 |ec A2 de |f2 fe f3/4g/a3/4 |\ne4 de |fd Be cA |dB Gd BG |F2 B2 BA |\nB3 A FA |]\r\r\n", "key": "Bmin", "type": "waltz", "unit": "1/8"}