{"title": "Lord Gordon's", "meter": "4/4", "version": 2, "link": "https://thesession.org/tunes/1774#setting15222", "tune": "dB |: AD (3FED A,DFB | AD (3FED FAdc | BE~E2 dE~E2 | BE~E2 BAFA |\ndcdf edef | (3ABA ^GB A2Bc | (3dcB (3cBA BFAF |1 EFGA BcdB :|2 EFGA Bcde ||\n|: f2 df afde | (3faf df a2 gf | efga bgec | dcBA GABc |\nd~f3 e~B3 | AFdF A2 Bc | dB (3cBA BFAF | EFGA Bcde :|\n|: fa (3aaa fdad | fa (3aaa fdad | fb(3bbb febe | fb(3bbb febe |\n~f3e ~d3B | (3ABA ^GB A2e(f | a)fec dBAF | EFGA Bcde :|\nAdcd fdcd |Adcd fdcd | egfg bgfg |egfg bgeg |\nfgfe dedB | (3ABA ^GB A2e(f | a)fec dBAF | EFGA BcdB |\nAd{e}dc defd | Ad{e}dc defd | eg{a}gf ~g3f | (3efg {a}gf ~g3f |\nfgfe dedB | (3ABA ^GB A2e(f | a)fec dBAF | EFGA Bcde |\n|: fa{b}a^g afde | fa{b}a^g afdf | gbef gbef | gbef gfef |\ngb(3bbb fa (3aaa |fedB ABdf | afec dBAF |1 EFGA BcdB :|2 EFGA B2 |\n\"Final Ending\"[G2B2] [F2A2] ||\r\r\n", "key": "Dmaj", "type": "reel", "unit": "1/8"}