{"title": "10th Bat Crossing Rhine", "meter": "6/8", "version": 2, "link": "https://thesession.org/tunes/7078#setting18649", "tune": "d>fA d2 f | f>ga f>ed | c2 e A>ce | e>fg f>ed |\rd>fA d2 f | f>ga f>ed | c2 e A>ce | d3 d2 :|\ra2 f d2 f | f<af f>ed | c2 e A>ce | e>fg f>ed |\ra2 f d2 f | f<af f>ed | c2 e A>ce | d3 d2 :|\rd3 A>df | f<af f>ed | c3 A>ce | e>fg f>ed |\rd3 A>df | f<af f>ed | c2 e A>ce | d3 d2 :|\ra2 a A>df | f<a3f f>ed | c2 e A>ce | e>fg f>ed |\ra2 a A>df | f<a3f f>ed | c2 e A>ce | d3 d2 :|\r\r\n", "key": "Amix", "type": "jig", "unit": "1/8"}