{"title": "Constitution Breakdown", "meter": "4/4", "version": 1, "link": "https://thesession.org/tunes/6071#setting6071", "tune": "|: Bc |\ndb b/b/b b2 fg | ag a/g/f g2 dc | Bdgd Bdgd | ec c/c/c cBAB |\nca a/a/a agga | gf-ff f3 f | efdf efdf | edBA G2 Bc |\nd/d/b b/b/b b2 fg | ag a/g/f g2 dc | Bdgd Bdgd | ec-c2 c3 F |\nE2 cE dEcE | D2 BD cDBD | DFAB cAFG | AG-GG G3 F |\nEc-cE dEcE | DB-BD cDBD | DFAB c/B/A FG | AG-GG G2 :|\n\n|: Bc |\ndb b/b/b b2 fg | aggf g2 dc | Bdgd Bdgd | ec c/c/c c2 AB |\nca a/a/a a2 ga | gffg f3 g | efdf efdf | edBA G2 Bc |\ndb b/b/b b2 fg | aggf g2 dc | Bdgd Bdgd | eccB c3 F |\nE/F/E cE dEcE | D/E/D BD cDBD | DFAB c/B/A FG | AGGF G3 F |\nE/F/E cE dEcE | D/E/D BD cDBD | DFAB c/B/A FG | AGGF GD :|\n\n|: A/B/c |\ndbzb bafg | agzg gedc | BdgB dgBd | eczB cBAB |\ncaza a2 ga | gf f2 f2 A/B/c | d/e/d ^cd edcd | edBG D2 A/B/c |\nd2 bb b2 fg | ag-gg gedc | BdgB dgBd | ec-cB c2 GF |\nEGcd cAGE | DB-Bc BAGE | DFAB cAFA | GFGA BAGF |\nEccd cAGE | DGBc BAGE | DFAB c/B/A FA | GEDB, G,2 :|\r\r\n", "key": "Gmaj", "type": "reel", "unit": "1/8"}