{"title": "Pilgrim Sunrise", "meter": "2/4", "version": 1, "link": "https://thesession.org/tunes/14957#setting27630", "tune": "G3 F | E3 C | FA cB | G3 E | FA cB | GA FD | EG FD | E3 c |\nBG EB | A3 B | AF DA | G3 G | FD B,A | GE CG | FD B,D | C4 |\nG3 F | E3 C | FA cB | G3 E | FA cB | GA FD | EG FD | E3 c |\nBG EB | A3 B | AF DA | G3 G | FD B,A | GE CG | FD B,D |\n\"^B\" C2 E/2F/2E/2F/2 |GC G/2A/2G/2F/2 | EC E/2F/2E/2F/2 | GC G/2A/2G/2F/2 |\nEC E/2F/2E/2F/2 | G/2A/2G/2A/2 B/2G/2A/2B/2 | c/2B/2c/2G/2 d/2c/2B/2A/2 | B/2A/2B/2G/2 c/2B/2A/2G/2 |\nA/2G/2A/2F/2 B/2A/2G/2F/2 | G/2F/2G/2E/2 A/2G/2F/2E/2 | F/2E/2F/2D/2 G/2F/2E/2D/2 | E/2D/2E/2C/2 F/2E/2D/2C/2 | D/2C/2D/2B,/2 E/2D/2C/2B,/2 |\n\"^C\" C2 EG | c2 d/2c/2B/2d/2 | cG EG | c2 d/2c/2B/2d/2 |\ncG EG | AG/2F/2 cA | GF/2E/2 cG | FE/2D/2 GG |\nC2 EG | c2 d/2c/2B/2d/2 | cG EG | c2 d/2c/2B/2d/2 |\ncG EG | AG/2F/2 cA | GF/2E/2 cG | FE/2D/2 GG | C3 E |\n\"^D\" G>E C/2D/2E/2F/2 | G>F DC | B,/2C/2D/2E/2 FA |\nA>G EC | G>E C/2D/2E/2F/2 | G>F DC | B,/2C/2D/2E/2 F/2D/2G |\nC3 E | G>E C/2D/2E/2F/2 | G>F DC | B,/2C/2D/2E/2 FA |\nA>G EC | G>E C/2D/2E/2F/2 | G>F DC | B,/2C/2D/2E/2 F/2D/2G | C4 |]\r\r\n", "key": "Cmaj", "type": "polka", "unit": "1/8"}