{"title": "Rakes Of Cashel, The", "meter": "6/8", "version": 1, "link": "https://thesession.org/tunes/12766#setting21622", "tune": "|: G2g gdg | gdg fdc | B2g abg | fdd cAF |\nG2g gdg | gdg fdc | B2b abg |1 fdd cAF :|2 fdd cAF ||\n|: ~B3 cBc | d2g gfa | ~B3 cBc | ded cAF |\n~B3 cBc | d2g gfe | fdd ecc |1 dBB cAA :|2 fdf cAF ||\n|: ~B3 GDG | G2g gdc | ~B3 GDG | GBd cAF |\n~B3 GDG | GBd gfe | fdd ecc |1 dBB cAA :|2 fdf cAF ||\n|: G2g abg | abg fdc | B2g abg | fdd cAF |\nG2g abg | abg g2e | fdd ecc |1 dBB cAA :|2 fdf cAF ||\n|: BFF cFF | dFF Bdg | BFF cFF | ded cAF |\nBFF cFF | dFF gfe | fdd ecc |1 dBB cAA :|2 gfd cAF ||\r\r\n", "key": "Gmin", "type": "jig", "unit": "1/8"}